{
  "positions": {
    "PLTR": {
      "qty": 0.19433324264448676,
      "entry": 128.645,
      "peak": 129.83,
      "entry_at": "2026-07-07T13:50:18Z"
    }
  },
  "cooldown": {
    "AMD": 3
  },
  "realized_pnl": -1.1914855950206844,
  "run_count": 5,
  "last_reflection_date": "2026-07-07",
  "trade_log": [
    {
      "sym": "MSTR",
      "pnl_pct": 0.0,
      "pnl_usd": 0.0,
      "reason": "NEWS-RISK",
      "closed_at": "2026-07-07T19:24:06Z"
    },
    {
      "sym": "AVGO",
      "pnl_pct": 0.0,
      "pnl_usd": 0.0,
      "reason": "NEWS-RISK",
      "closed_at": "2026-07-07T19:24:08Z"
    },
    {
      "sym": "AMD",
      "pnl_pct": -0.04765942380082738,
      "pnl_usd": -1.1914855950206844,
      "reason": "GR-STOP",
      "closed_at": "2026-07-08T18:04:47Z"
    }
  ],
  "consec_losses": 3,
  "position_schema_seen": [
    "id",
    "symbol",
    "market",
    "token_id",
    "outcome",
    "side",
    "quantity",
    "entry_price",
    "current_price",
    "pnl",
    "source",
    "opened_at"
  ],
  "news": {
    "AMD": {
      "at": "2026-07-08T18:04:42Z",
      "score": 0,
      "worst": null,
      "items": [
        {
          "title": "Nvidia's valuation just hit a multiyear low \u2014 even as revenue sets records",
          "pubDate": "Wed, 08 Jul 2026 15:59:48 +0000",
          "link": "https://finance.yahoo.com/technology/article/nvidias-valuation-just-hit-a-multiyear-low--even-as-revenue-sets-records-155948933.html?.tsrc=rss"
        },
        {
          "title": "Arm Holdings' Licensing Momentum Continues to Fuel Revenue Growth",
          "pubDate": "Wed, 08 Jul 2026 15:26:00 +0000",
          "link": "https://finance.yahoo.com/technology/articles/arm-holdings-licensing-momentum-continues-152600229.html?.tsrc=rss"
        },
        {
          "title": "Here\u2019s What Analysts Say About Advanced Micro Devices, Inc.\u00a0(AMD)",
          "pubDate": "Wed, 08 Jul 2026 14:48:35 +0000",
          "link": "https://finance.yahoo.com/markets/stocks/articles/analysts-advanced-micro-devices-inc-144835687.html?.tsrc=rss"
        },
        {
          "title": "SpaceX Stock Slides to its Lowest Levels Since IPO: Buy the Dip?",
          "pubDate": "Wed, 08 Jul 2026 13:58:00 +0000",
          "link": "https://finance.yahoo.com/markets/stocks/articles/spacex-stock-slides-lowest-levels-135800338.html?.tsrc=rss"
        },
        {
          "title": "Intel vs. Silicon Motion: Which Semiconductor Stock is the Better Buy?",
          "pubDate": "Wed, 08 Jul 2026 13:44:00 +0000",
          "link": "https://finance.yahoo.com/technology/articles/intel-vs-silicon-motion-semiconductor-134400520.html?.tsrc=rss"
        },
        {
          "title": "Nvidia, Micron, AMD Lead Chip Stock Selloff After Trump Said U.S.-Iran 'Truce Is Over'",
          "pubDate": "Wed, 08 Jul 2026 13:21:26 +0000",
          "link": "https://finance.yahoo.com/technology/articles/nvidia-micron-amd-lead-chip-132126893.html?.tsrc=rss"
        },
        {
          "title": "AI memory stocks trim losses as investors buy the dip",
          "pubDate": "Wed, 08 Jul 2026 12:28:48 +0000",
          "link": "https://finance.yahoo.com/markets/stocks/article/ai-memory-stocks-trim-losses-as-investors-buy-the-dip-122848703.html?.tsrc=rss"
        },
        {
          "title": "Advanced Micro Devices (AMD): Top 10 Best Stock to Buy in Glen Kacher\u2019s Portfolio",
          "pubDate": "Wed, 08 Jul 2026 12:00:42 +0000",
          "link": "https://finance.yahoo.com/markets/stocks/articles/advanced-micro-devices-amd-top-120042016.html?.tsrc=rss"
        }
      ]
    },
    "PLTR": {
      "at": "2026-07-08T18:04:43Z",
      "score": 1,
      "worst": null,
      "items": [
        {
          "title": "Why Palantir Technologies Stock Just Dropped",
          "pubDate": "Wed, 08 Jul 2026 17:55:43 +0000",
          "link": "https://www.fool.com/investing/2026/07/08/why-palantir-technologies-stock-just-dropped/?.tsrc=rss"
        },
        {
          "title": "Palantir Leads Software Stocks Lower",
          "pubDate": "Wed, 08 Jul 2026 17:48:44 +0000",
          "link": "https://finance.yahoo.com/markets/stocks/articles/palantir-leads-software-stocks-lower-174844080.html?.tsrc=rss"
        },
        {
          "title": "'Sticker Shock' Powers Open-Source AI Growth. What It Means For Top AI Stocks.",
          "pubDate": "Wed, 08 Jul 2026 17:27:47 +0000",
          "link": "https://finance.yahoo.com/m/3e68c70d-cb74-3273-99d9-e3c7c7d332d7/%27sticker-shock%27-powers.html?.tsrc=rss"
        },
        {
          "title": "Palantir Just Hit $300 Billion. The Numbers Say That\u2019s Only the Start.",
          "pubDate": "Wed, 08 Jul 2026 17:02:36 +0000",
          "link": "https://247wallst.com/investing/2026/07/08/palantir-just-hit-300-billion-the-numbers-say-thats-only-the-start/?.tsrc=rss"
        },
        {
          "title": "Palantir Stock\u2019s 25% Rally Is in Jeopardy as Shares Slide",
          "pubDate": "Wed, 08 Jul 2026 15:59:00 +0000",
          "link": "https://finance.yahoo.com/m/c739ca51-777b-3006-b957-1e48d0ec4333/palantir-stock%E2%80%99s-25%25-rally-is.html?.tsrc=rss"
        },
        {
          "title": "Palantir Technologies (PLTR) Looks Beaten Down Despite Expanding Its Sovereign AI Push",
          "pubDate": "Wed, 08 Jul 2026 15:50:17 +0000",
          "link": "https://finance.yahoo.com/technology/ai/articles/palantir-technologies-pltr-looks-beaten-155017246.html?.tsrc=rss"
        },
        {
          "title": "Ondas Just Built Autonomous Defense Powerhouse With This Major Acquisition",
          "pubDate": "Wed, 08 Jul 2026 15:25:39 +0000",
          "link": "https://finance.yahoo.com/technology/articles/ondas-just-built-autonomous-defense-152539794.html?.tsrc=rss"
        },
        {
          "title": "Here is why Palantir Technologies Inc.\u00a0(PLTR)\u00a0is among the 12 Best Cybersecurity Stocks to Buy and Hold for the Long Term",
          "pubDate": "Wed, 08 Jul 2026 14:48:22 +0000",
          "link": "https://finance.yahoo.com/technology/ai/articles/why-palantir-technologies-inc-pltr-144822979.html?.tsrc=rss"
        }
      ]
    },
    "MSTR": {
      "at": "2026-07-08T18:04:43Z",
      "score": 0,
      "worst": null,
      "items": [
        {
          "title": "Why MSTR Stock Is Down Despite a New Buy Rating",
          "pubDate": "Wed, 08 Jul 2026 17:25:00 +0000",
          "link": "https://finance.yahoo.com/m/81907a55-fb82-30bd-9298-0dd84e8018be/why-mstr-stock-is-down.html?.tsrc=rss"
        },
        {
          "title": "Top 3 Crypto Treasury Stocks to Watch Near Key Support Levels",
          "pubDate": "Wed, 08 Jul 2026 16:00:00 +0000",
          "link": "https://beincrypto.com/top-3-crypto-treasury-stocks-to-watch-near-key-support-levels/?.tsrc=rss"
        },
        {
          "title": "This is why Citi Cut Strategy Inc. (MSTR) Price Target But Asserted Buy Rating",
          "pubDate": "Wed, 08 Jul 2026 15:51:18 +0000",
          "link": "https://finance.yahoo.com/markets/stocks/articles/why-citi-cut-strategy-inc-155118325.html?.tsrc=rss"
        },
        {
          "title": "Bitcoin Drops After Trump Says U.S.-Iran Cease-Fire Is Over",
          "pubDate": "Wed, 08 Jul 2026 13:40:00 +0000",
          "link": "https://finance.yahoo.com/m/3dbf3385-2c8e-36ce-b132-e7947e53fae7/bitcoin-drops-after-trump.html?.tsrc=rss"
        },
        {
          "title": "Is It Worth Investing in Strategy (MSTR) Based on Wall Street's Bullish Views?",
          "pubDate": "Wed, 08 Jul 2026 13:30:03 +0000",
          "link": "https://finance.yahoo.com/markets/stocks/articles/worth-investing-strategy-mstr-based-133003884.html?.tsrc=rss"
        },
        {
          "title": "MSTR, XYZ Stocks Slide \u2013 Barclays Issues \u2018Overweight\u2019 Ratings But Pins Strategy Target Way Below Street",
          "pubDate": "Wed, 08 Jul 2026 13:27:21 +0000",
          "link": "https://stocktwits.com/news-articles/markets/cryptocurrency/mstr-xyz-stocks-fall-bitcoin-stock-market-sell-off-overshadow-barclays/cZmVAwNR7NF?.tsrc=rss"
        },
        {
          "title": "Eric Trump Under Fire For 'Buy The Dip' Posts as He Celebrates American Bitcoin Surpassing 8,000 BTC",
          "pubDate": "Wed, 08 Jul 2026 13:02:16 +0000",
          "link": "https://www.ccn.com/news/crypto/eric-trump-buy-dip-posts-celebrates-american-bitcoin/?.tsrc=rss"
        },
        {
          "title": "Strategy Just Unveiled a Brand-New Approach to Bitcoin. Is the World's Biggest Bitcoin Treasury Company in Trouble?",
          "pubDate": "Wed, 08 Jul 2026 11:14:00 +0000",
          "link": "https://www.fool.com/investing/2026/07/08/strategy-just-unveiled-a-brand-new-approach-to-bit/?.tsrc=rss"
        }
      ]
    },
    "AVGO": {
      "at": "2026-07-08T18:04:44Z",
      "score": 5,
      "worst": null,
      "items": [
        {
          "title": "Update: Wall Street Falls Intraday as Trump Threatens to Hit Iran Again",
          "pubDate": "Wed, 08 Jul 2026 17:39:46 +0000",
          "link": "https://finance.yahoo.com/markets/stocks/articles/wall-street-falls-intraday-trump-173946257.html?.tsrc=rss"
        },
        {
          "title": "Sector Update: Tech Stocks Rise Wednesday Afternoon",
          "pubDate": "Wed, 08 Jul 2026 17:39:27 +0000",
          "link": "https://finance.yahoo.com/technology/articles/sector-tech-stocks-rise-wednesday-173927838.html?.tsrc=rss"
        },
        {
          "title": "Veteran analyst drops massive Micron valuation prediction",
          "pubDate": "Wed, 08 Jul 2026 17:33:00 +0000",
          "link": "https://www.thestreet.com/investing/stocks/mu-micron-trillion-dollar-prediction-melius-research?.tsrc=rss"
        },
        {
          "title": "Apple\u2019s $30 Billion Chip Deal Boosts Broadcom Stock",
          "pubDate": "Wed, 08 Jul 2026 17:25:00 +0000",
          "link": "https://finance.yahoo.com/m/fbf71dd2-95ce-395b-8ea3-f2f3e8e9c967/apple%E2%80%99s-%2430-billion-chip-deal.html?.tsrc=rss"
        },
        {
          "title": "Tim Cook\u2019s Final Move as Apple CEO: The Biggest American Manufacturing Deal in Company History",
          "pubDate": "Wed, 08 Jul 2026 16:53:04 +0000",
          "link": "https://247wallst.com/investing/2026/07/08/tim-cooks-final-move-as-apple-ceo-the-biggest-american-manufacturing-deal-in-company-history/?.tsrc=rss"
        },
        {
          "title": "Micron, Broadcom, Valero Energy, Delta, SpaceX, and More Stocks That Explain Today\u2019s Market",
          "pubDate": "Wed, 08 Jul 2026 16:26:00 +0000",
          "link": "https://finance.yahoo.com/m/ee22eb1b-8aea-3ddf-9562-a1cf94ef28af/micron%2C-broadcom%2C-valero.html?.tsrc=rss"
        },
        {
          "title": "Broadcom Stock Jumps After Apple Extends Multibillion-Dollar Chip Deal",
          "pubDate": "Wed, 08 Jul 2026 16:25:00 +0000",
          "link": "https://finance.yahoo.com/markets/stocks/articles/broadcom-stock-jumps-apple-extends-162500170.html?.tsrc=rss"
        },
        {
          "title": "Apple Expands Broadcom Deal Beyond $30 Billion, Shares Rise 5%",
          "pubDate": "Wed, 08 Jul 2026 16:22:11 +0000",
          "link": "https://finance.yahoo.com/markets/stocks/articles/apple-expands-broadcom-deal-beyond-162211002.html?.tsrc=rss"
        }
      ]
    },
    "COIN": {
      "at": "2026-07-08T18:04:44Z",
      "score": 0,
      "worst": null,
      "items": [
        {
          "title": "Trump declares Iran ceasefire over; bitcoin and crypto markets drop",
          "pubDate": "Wed, 08 Jul 2026 16:54:57 +0000",
          "link": "https://finance.yahoo.com/video/trump-declares-iran-ceasefire-over-bitcoin-and-crypto-markets-drop-165457473.html?.tsrc=rss"
        },
        {
          "title": "ETHA vs. IBIT: Does Ethereum or Bitcoin Belong in Your Portfolio?",
          "pubDate": "Wed, 08 Jul 2026 16:02:22 +0000",
          "link": "https://247wallst.com/investing/etf/2026/07/08/etha-vs-ibit-does-ethereum-or-bitcoin-belong-in-your-portfolio/?.tsrc=rss"
        },
        {
          "title": "Top 3 Crypto Treasury Stocks to Watch Near Key Support Levels",
          "pubDate": "Wed, 08 Jul 2026 16:00:00 +0000",
          "link": "https://beincrypto.com/top-3-crypto-treasury-stocks-to-watch-near-key-support-levels/?.tsrc=rss"
        },
        {
          "title": "SpaceX Sparks Bitcoin Speculation With $88 Test Transfer To Coinbase After Six Months Of Wallet Silence",
          "pubDate": "Wed, 08 Jul 2026 15:24:40 +0000",
          "link": "https://stocktwits.com/news-articles/markets/cryptocurrency/spacex-bitcoin-wallet-test-coinbase/cZmVHGFR7NM?.tsrc=rss"
        },
        {
          "title": "Bitcoin Drops After Trump Says U.S.-Iran Cease-Fire Is Over",
          "pubDate": "Wed, 08 Jul 2026 13:40:00 +0000",
          "link": "https://finance.yahoo.com/m/3dbf3385-2c8e-36ce-b132-e7947e53fae7/bitcoin-drops-after-trump.html?.tsrc=rss"
        },
        {
          "title": "SpaceX Shifts Bitcoin Out Of Crypto Wallet",
          "pubDate": "Wed, 08 Jul 2026 13:31:00 +0000",
          "link": "https://www.cryptoprowl.com/releases/spacex-shifts-bitcoin-out-of-crypto-wallet-6098?.tsrc=rss"
        },
        {
          "title": "Analyst revamps Coinbase on Bitcoin outlook",
          "pubDate": "Wed, 08 Jul 2026 13:30:00 +0000",
          "link": "https://www.thestreet.com/crypto/markets/analyst-revamps-coinbase-on-bitcoin-outlook?.tsrc=rss"
        },
        {
          "title": "Coinbase Global Earnings Preview: What to Expect",
          "pubDate": "Wed, 08 Jul 2026 11:26:58 +0000",
          "link": "https://www.barchart.com/story/news/3181412/coinbase-global-earnings-preview-what-to-expect?.tsrc=rss"
        }
      ]
    }
  }
}